gsheet_image_generator/__init__.py
gsheet_image_generator/__main__.py
gsheet_image_generator/gsheet_image.py
gsheet_image_generator/gsheet_image_generator.py
gsheet_image_generator-1.0.0.dist-info/LICENSE
gsheet_image_generator-1.0.0.dist-info/METADATA
gsheet_image_generator-1.0.0.dist-info/WHEEL
gsheet_image_generator-1.0.0.dist-info/top_level.txt
gsheet_image_generator-1.0.0.dist-info/RECORD
