Metadata-Version: 2.1
Name: gsheet-image-generator
Version: 1.0.0
Summary: An awesome package which helps us in creating a graph from Google Sheets and stores them as image
Home-page: https://github.com/shivachandrakante/gsheet_image_generator
Author: shivachandra
Author-email: k.s9908725092@gmail.com
License: LICENSE
Keywords: spreadhseets google api v4 wrapper csv pandas image_generator
Platform: any
Requires-Python: >=2.7,!=3.0.*,!=3.1.*,!=3.2.*,!=3.3.*,!=3.4.*,!=3.5.*
Requires-Dist: google-auth-oauthlib (==0.4.1)
Requires-Dist: google-auth-httplib2 (==0.0.4)
Requires-Dist: gsheets (>=0.5.1)
Requires-Dist: numpy
Requires-Dist: pandas
Requires-Dist: matplotlib
Requires-Dist: seaborn
Requires-Dist: oauth2client (>=1.5.0)
Requires-Dist: google-api-python-client (<1.8) ; python_version < "3"
Requires-Dist: google-api-python-client ; python_version >= "3"
